thercy/__init__.py
thercy/constants.py
thercy/utils.py
thercy/cycles/__init__.py
thercy/cycles/builder.py
thercy/cycles/cycle.py
thercy/cycles/_parts/__init__.py
thercy/cycles/_parts/base_part.py
thercy/cycles/_parts/condenser.py
thercy/cycles/_parts/evaporator.py
thercy/cycles/_parts/heat_exchanger.py
thercy/cycles/_parts/heater_closed.py
thercy/cycles/_parts/heater_closed_real.py
thercy/cycles/_parts/heater_open.py
thercy/cycles/_parts/pump.py
thercy/cycles/_parts/steam_generator.py
thercy/cycles/_parts/trap.py
thercy/cycles/_parts/turbine.py
thercy/state/__init__.py
thercy/state/state_cycle.py
thercy/state/state_graph.py
thercy-0.0.2.dist-info/METADATA
thercy-0.0.2.dist-info/WHEEL
thercy-0.0.2.dist-info/licenses/LICENSE
thercy-0.0.2.dist-info/RECORD
