Metadata-Version: 2.3
Name: thercy
Version: 0.0.2
Summary: Thermodynamic cycles solver package
Project-URL: Homepage, https://github.com/mBelisarius/thercy
Project-URL: Issues, https://github.com/mBelisarius/thercy/issues
Author: Marcos A. Belizario
Maintainer: Marcos A. Belizario
License: Creative Commons Legal Code
License-File: LICENSE
Classifier: License :: CC0 1.0 Universal (CC0 1.0) Public Domain Dedication
Classifier: Operating System :: OS Independent
Classifier: Programming Language :: Python :: 3
Requires-Python: >=3.10
